harvesters_gui/__init__.py
harvesters_gui/_helper.py
harvesters_gui/_version.py
harvesters_gui/_private/__init__.py
harvesters_gui/_private/frontend/__init__.py
harvesters_gui/_private/frontend/canvas.py
harvesters_gui/_private/frontend/helper.py
harvesters_gui/_private/frontend/image/__init__.py
harvesters_gui/_private/frontend/image/background/__init__.py
harvesters_gui/_private/frontend/image/background/about.jpg
harvesters_gui/_private/frontend/image/icon/__init__.py
harvesters_gui/_private/frontend/image/icon/about.png
harvesters_gui/_private/frontend/image/icon/add_file.png
harvesters_gui/_private/frontend/image/icon/collapse.png
harvesters_gui/_private/frontend/image/icon/connect.png
harvesters_gui/_private/frontend/image/icon/device_attribute.png
harvesters_gui/_private/frontend/image/icon/disconnect.png
harvesters_gui/_private/frontend/image/icon/edit_list.png
harvesters_gui/_private/frontend/image/icon/expand.png
harvesters_gui/_private/frontend/image/icon/genicam_logo.png
harvesters_gui/_private/frontend/image/icon/genicam_logo_i.png
harvesters_gui/_private/frontend/image/icon/open_file.png
harvesters_gui/_private/frontend/image/icon/pause.png
harvesters_gui/_private/frontend/image/icon/select_file.png
harvesters_gui/_private/frontend/image/icon/start_acquisition.png
harvesters_gui/_private/frontend/image/icon/stop_acquisition.png
harvesters_gui/_private/frontend/image/icon/update.png
harvesters_gui/_private/frontend/pyqt5/__init__.py
harvesters_gui/_private/frontend/pyqt5/about.py
harvesters_gui/_private/frontend/pyqt5/action.py
harvesters_gui/_private/frontend/pyqt5/attribute_controller.py
harvesters_gui/_private/frontend/pyqt5/device_list.py
harvesters_gui/_private/frontend/pyqt5/display_rate_list.py
harvesters_gui/_private/frontend/pyqt5/feature_tree.py
harvesters_gui/_private/frontend/pyqt5/helper.py
harvesters_gui/_private/frontend/pyqt5/icon.py
harvesters_gui/_private/frontend/pyqt5/thread.py
harvesters_gui/frontend/__init__.py
harvesters_gui-1.1.0.dist-info/LICENSE.txt
harvesters_gui-1.1.0.dist-info/METADATA
harvesters_gui-1.1.0.dist-info/WHEEL
harvesters_gui-1.1.0.dist-info/top_level.txt
harvesters_gui-1.1.0.dist-info/RECORD
