Metadata-Version: 2.1
Name: harvesters-gui
Version: 1.1.0
Summary: Graphical user interfce of Harvester
Home-page: https://github.com/genicam/harvesters_gui
Download-URL: https://pypi.org/project/harvesters_gui/
Author: The GenICam Committee
Author-email: genicam@list.stemmer-imaging.com
License: Apache Software License V2.0
Platform: any
Classifier: Development Status :: 3 - Alpha
Classifier: Intended Audience :: Science/Research
Classifier: Intended Audience :: Education
Classifier: Intended Audience :: Developers
Classifier: License :: OSI Approved :: Apache Software License
Classifier: Operating System :: MacOS :: MacOS X
Classifier: Operating System :: Microsoft :: Windows
Classifier: Operating System :: POSIX
Provides: harvesters_gui
License-File: LICENSE.txt
Requires-Dist: vispy (<=0.6)
Requires-Dist: harvesters (>=1.4.1)
